{"religionGroups":[{"name":"christian","defenderOfFaith":true,"canFormPersonalUnions":true,"religions":[{"name":"catholic","color":{"red":204,"green":204,"blue":0},"country":{"tolerance_own":"1","tolerance_heretic":"-1"},"secondaryCountry":{"diplomatic_reputation":"1","advisor_pool":"1"}},{"name":"anglican","color":{"red":135,"green":77,"blue":255},"country":{"development_cost":"-0.1","innovativeness_gain":"0.5"},"secondaryCountry":{"idea_cost":"-0.1"}},{"name":"hussite","color":{"red":244,"green":55,"blue":9},"country":{"shock_damage_received":"-0.05","global_heretic_missionary_strength":"0.02"},"secondaryCountry":{"shock_damage_received":"-0.025"}},{"name":"protestant","color":{"red":0,"green":0,"blue":178},"country":{"global_tax_modifier":"0.1","improve_relation_modifier":"0.15","church_loyalty_modifier":"0.1"},"secondaryCountry":{"idea_cost":"-0.1"}},{"name":"reformed","color":{"red":76,"green":76,"blue":229},"country":{"tolerance_heretic":"2","advisor_pool":"1"},"secondaryCountry":{"global_unrest":"-1","advisor_cost":"-0.1"}},{"name":"orthodox","color":{"red":178,"green":127,"blue":0},"country":{"stability_cost_modifier":"-0.1","tolerance_own":"1"},"secondaryCountry":{"global_colonial_growth":"10","tolerance_own":"1"},"province":{"local_missionary_strength":"-0.01"}},{"name":"coptic","color":{"red":178,"green":38,"blue":76},"country":{"defensiveness":"0.1","tolerance_own":"1"},"secondaryCountry":{"siege_ability":"0.1","defensiveness":"0.1"},"province":{"local_missionary_strength":"-0.02"}}]},{"name":"muslim","defenderOfFaith":true,"canFormPersonalUnions":false,"religions":[{"name":"sunni","color":{"red":0,"green":153,"blue":0},"country":{"cav_to_inf_ratio":"0.10","heir_chance":"1.0"},"secondaryCountry":{"trade_efficiency":"0.1","heir_chance":"1.0"},"province":{"local_missionary_strength":"-0.02"}},{"name":"shiite","color":{"red":0,"green":204,"blue":0},"country":{"heir_chance":"1.0","land_morale":"0.05"},"secondaryCountry":{"land_morale":"0.05","advisor_cost":"-0.1"},"province":{"local_missionary_strength":"-0.02"}},{"name":"ibadi","color":{"red":0,"green":102,"blue":0},"country":{"heir_chance":"1.0","global_trade_goods_size_modifier":"0.1"},"secondaryCountry":{"global_ship_cost":"-0.1","advisor_cost":"-0.1"},"province":{"local_missionary_strength":"-0.02"}}]},{"name":"eastern","defenderOfFaith":false,"canFormPersonalUnions":false,"religions":[{"name":"buddhism","color":{"red":204,"green":76,"blue":0},"country":{"tolerance_heretic":"2","advisor_cost":"-0.1"},"secondaryCountry":{"development_cost":"-0.1","diplomats":"1"}},{"name":"vajrayana","color":{"red":204,"green":76,"blue":76},"country":{"tolerance_heretic":"1","land_morale":"0.05"},"secondaryCountry":{"horde_unity":"1","tolerance_own":"1"}},{"name":"mahayana","color":{"red":204,"green":76,"blue":127},"country":{"tolerance_heretic":"2","idea_cost":"-0.05"},"secondaryCountry":{"global_tax_modifier":"0.1","tolerance_heathen":"2"}},{"name":"confucianism","color":{"red":214,"green":229,"blue":140},"country":{"tolerance_heretic":"2","adm_tech_cost_modifier":"-0.1"},"secondaryCountry":{"adm_tech_cost_modifier":"-0.1","stability_cost_modifier":"-0.1"}},{"name":"shinto","color":{"red":204,"green":0,"blue":0},"country":{"land_morale":"0.1"},"secondaryCountry":{"discipline":"0.05","global_unrest":"-1"},"province":{"local_missionary_strength":"-0.02"}}]},{"name":"dharmic","defenderOfFaith":false,"canFormPersonalUnions":false,"religions":[{"name":"hinduism","color":{"red":0,"green":204,"blue":204},"country":{"tolerance_heathen":"1","tolerance_own":"1","brahmins_hindu_influence_modifier":"0.2"},"secondaryCountry":{"tolerance_heretic":"1","tolerance_heathen":"2"}},{"name":"sikhism","color":{"red":0,"green":153,"blue":153},"country":{"mil_tech_cost_modifier":"-0.1","land_morale":"0.1"},"secondaryCountry":{"land_morale":"0.05","global_unrest":"-1"},"province":{"local_missionary_strength":"-0.01"}}]},{"name":"pagan","defenderOfFaith":false,"canFormPersonalUnions":false,"religions":[{"name":"animism","color":{"red":127,"green":0,"blue":0},"country":{"tolerance_own":"1","global_unrest":"-1"},"secondaryCountry":{"tolerance_own":"2","loot_amount":"0.25"},"province":{"local_missionary_strength":"0.02"}},{"name":"shamanism","color":{"red":127,"green":76,"blue":76},"country":{"tolerance_heathen":"2","diplomatic_reputation":"1"},"secondaryCountry":{"tolerance_own":"2","loot_amount":"0.25"},"province":{"local_missionary_strength":"0.02"}},{"name":"totemism","color":{"red":127,"green":115,"blue":115},"country":{"tolerance_own":"1","global_unrest":"-1"},"secondaryCountry":{"tolerance_own":"2","loot_amount":"0.25"},"province":{"local_missionary_strength":"0.02"}},{"name":"inti","color":{"red":64,"green":115,"blue":115},"country":{"tolerance_own":"1","global_autonomy":"-0.05"},"secondaryCountry":{"tolerance_own":"1","global_autonomy":"-0.05"},"province":{"local_missionary_strength":"0.02"}},{"name":"nahuatl","color":{"red":64,"green":115,"blue":64},"country":{"land_morale":"0.1","global_unrest":"-2","burghers_influence_modifier":"-0.05"},"secondaryCountry":{"land_morale":"0.05","raze_power_gain":"0.2"},"province":{"local_missionary_strength":"0.02"}},{"name":"mesoamerican_religion","color":{"red":127,"green":25,"blue":178},"country":{"tolerance_own":"1","advisor_pool":"1"},"secondaryCountry":{"advisor_pool":"1","stability_cost_modifier":"-0.1"},"province":{"local_missionary_strength":"0.02"}},{"name":"norse_pagan_reformed","color":{"red":191,"green":191,"blue":191},"country":{"land_forcelimit_modifier":"0.10","naval_forcelimit_modifier":"0.10"},"secondaryCountry":{"merc_maintenance_modifier":"-0.1","galley_power":"0.2"},"province":{"local_missionary_strength":"0.02"}},{"name":"tengri_pagan_reformed","color":{"red":25,"green":76,"blue":217},"country":{"cav_to_inf_ratio":"0.25","global_regiment_cost":"-0.2"}}]},{"name":"jewish_group","defenderOfFaith":false,"canFormPersonalUnions":false,"religions":[{"name":"jewish","color":{"red":153,"green":25,"blue":102},"country":{"tolerance_own":"2","advisor_pool":"1"},"secondaryCountry":{"advisor_pool":"1","advisor_cost":"-0.1"},"province":{"local_missionary_strength":"-0.02"}}]},{"name":"zoroastrian_group","defenderOfFaith":false,"canFormPersonalUnions":false,"religions":[{"name":"zoroastrian","color":{"red":127,"green":178,"blue":51},"country":{"tolerance_own":"2","trade_efficiency":"0.1"},"secondaryCountry":{"merchants":"1","tolerance_own":"1"},"province":{"local_missionary_strength":"-0.02"}}]},{"name":"christian","defenderOfFaith":false,"canFormPersonalUnions":false,"religions":[{"name":"cathar","color":{"red":0,"green":0,"blue":1},"country":{"tolerance_own":"2","stability_cost_modifier":"-0.1","may_recruit_female_generals":"yes","female_advisor_chance":"0.2"},"secondaryCountry":{"yearly_corruption":"-0.1","advisor_pool":"1"}},{"name":"fraticelli","color":{"red":1,"green":1,"blue":0},"country":{"legitimacy":"1","tolerance_own":"2"},"secondaryCountry":{"horde_unity":"1","tolerance_own":"1"},"province":{"local_tax_modifier":"-0.1"}},{"name":"messalian","color":{"red":1,"green":0,"blue":0},"country":{"global_missionary_strength":"0.01","heir_chance":"1","may_recruit_female_generals":"yes","female_advisor_chance":"0.2"},"secondaryCountry":{"global_missionary_strength":"0.01","advisor_cost":"-0.1"},"province":{"local_missionary_strength":"-0.01"}},{"name":"waldensian","color":{"red":0,"green":0,"blue":1},"country":{"tolerance_heretic":"2","technology_cost":"-0.1"},"secondaryCountry":{"global_unrest":"-1","technology_cost":"-0.1"}},{"name":"lollard","color":{"red":0,"green":1,"blue":1},"country":{"tolerance_own":"2","stability_cost_modifier":"-0.2"},"secondaryCountry":{"stability_cost_modifier":"-0.2"},"province":{"local_tax_modifier":"-0.1"}},{"name":"monophysite","color":{"red":1,"green":0,"blue":0},"country":{"global_tax_modifier":"0.1","tolerance_own":"2"},"secondaryCountry":{"global_tax_modifier":"0.25"},"province":{"local_missionary_strength":"-0.02"}},{"name":"bogomilist","color":{"red":1,"green":0,"blue":0},"country":{"stability_cost_modifier":"-0.1","land_morale":"0.1"},"secondaryCountry":{"stability_cost_modifier":"-0.10","tolerance_own":"1"},"province":{"local_missionary_strength":"-0.02","local_unrest":"-1"}},{"name":"monothelite","color":{"red":0,"green":0,"blue":0},"country":{"tolerance_own":"2","global_autonomy":"-0.05"},"secondaryCountry":{"tolerance_own":"1","global_autonomy":"-0.05"},"province":{"local_missionary_strength":"-0.01"}},{"name":"iconoclast","color":{"red":0,"green":0,"blue":0},"country":{"tolerance_heretic":"-2","tolerance_own":"4"},"secondaryCountry":{"raze_power_gain":"0.2","global_missionary_strength":"0.01"},"province":{"local_missionary_strength":"-0.01"}},{"name":"paulician","color":{"red":0,"green":0,"blue":0},"country":{"stability_cost_modifier":"-0.2","tolerance_heathen":"2"},"secondaryCountry":{"merc_maintenance_modifier":"-0.1","global_regiment_cost":"-0.1"},"province":{"local_missionary_strength":"-0.01"}}]},{"name":"muslim","defenderOfFaith":false,"canFormPersonalUnions":false,"religions":[{"name":"zikri","color":{"red":0,"green":1,"blue":0},"country":{"global_institution_spread":"0.15","heir_chance":"1.0"},"secondaryCountry":{"global_institution_spread":"0.15","heir_chance":"1.0"},"province":{"local_missionary_strength":"-0.02"}},{"name":"yazidi","color":{"red":0,"green":0,"blue":1},"country":{"tolerance_own":"3","tolerance_heretic":"-1","tolerance_heathen":"-1","advisor_pool":"1","global_missionary_strength":"-0.01"},"secondaryCountry":{"tolerance_own":"2","advisor_pool":"1"},"province":{"local_missionary_strength":"-0.01"}},{"name":"kharijite","color":{"red":0,"green":1,"blue":1},"country":{"improve_relation_modifier":"0.2","heir_chance":"1.0"},"secondaryCountry":{"advisor_cost":"-0.1","improve_relation_modifier":"0.1"},"province":{"local_missionary_strength":"-0.02"}},{"name":"druze","color":{"red":0,"green":1,"blue":0},"country":{"heir_chance":"1.0","dip_tech_cost_modifier":"-0.1","tolerance_heretic":"-1"},"secondaryCountry":{"diplomats":"1","dip_tech_cost_modifier":"-0.05"},"province":{"local_missionary_strength":"-0.02"}},{"name":"hurufi","color":{"red":0,"green":1,"blue":0},"country":{"heir_chance":"1.0","diplomatic_upkeep":"2"},"secondaryCountry":{"diplomatic_upkeep":"1","stability_cost_modifier":"-0.1"},"province":{"local_missionary_strength":"-0.01"}}]},{"name":"zoroastrian_group","defenderOfFaith":false,"canFormPersonalUnions":false,"religions":[{"name":"mazdaki","color":{"red":0,"green":1,"blue":0},"country":{"global_unrest":"-3","tolerance_heretic":"1","tolerance_heathen":"1","global_tax_modifier":"-0.15"},"secondaryCountry":{"global_unrest":"-1","tolerance_heretic":"1"}},{"name":"manichean","color":{"red":0,"green":1,"blue":0},"country":{"tolerance_heathen":"2","legitimacy":"1"},"secondaryCountry":{"tolerance_heathen":"2","global_missionary_strength":"0.01"}},{"name":"khurmazta","color":{"red":0,"green":1,"blue":0},"country":{"stability_cost_modifier":"-0.1","global_tax_modifier":"0.1"},"secondaryCountry":{"stability_cost_modifier":"-0.1","global_tax_modifier":"0.1"}}]},{"name":"jewish_group","defenderOfFaith":false,"canFormPersonalUnions":false,"religions":[{"name":"samaritan_faith","color":{"red":0,"green":1,"blue":0},"country":{"advisor_cost":"-0.15","adm_tech_cost_modifier":"-0.05","tolerance_heathen":"-2"},"secondaryCountry":{"advisor_cost":"-0.3"},"province":{"local_missionary_strength":"-0.01","local_tax_modifier":"0.02"}},{"name":"karaite_faith","color":{"red":0,"green":1,"blue":0},"country":{"governing_capacity":"250","idea_cost":"-0.1","tolerance_heathen":"-2"},"secondaryCountry":{"land_morale":"0.05","global_unrest":"-1"},"province":{"local_missionary_strength":"-0.01","local_tax_modifier":"0.02"}}]},{"name":"cannorian","defenderOfFaith":true,"canFormPersonalUnions":true,"religions":[{"name":"cannorian_pantheon","color":{"red":204,"green":204,"blue":204},"country":{"tolerance_heathen":"2","tolerance_heretic":"2","tolerance_own":"1"},"secondaryCountry":{"tolerance_heathen":"2","tolerance_heretic":"1"}},{"name":"regent_court","color":{"red":204,"green":204,"blue":204},"country":{"tolerance_heathen":"2","tolerance_heretic":"1"},"secondaryCountry":{"tolerance_heathen":"2"}},{"name":"corinite","color":{"red":230,"green":65,"blue":55},"country":{"leader_land_shock":"1","land_morale":"0.1"},"secondaryCountry":{"land_morale":"0.05"}},{"name":"ravelian","color":{"red":204,"green":204,"blue":0},"country":{"tolerance_own":"2","tolerance_heretic":"-2"},"secondaryCountry":{"tolerance_own":"1","tolerance_heretic":"-1"}}]},{"name":"faithless","defenderOfFaith":false,"canFormPersonalUnions":false,"religions":[{"name":"the_thought","color":{"red":198,"green":182,"blue":212},"country":{"tolerance_heathen":"2","adm_tech_cost_modifier":"-0.1","artificers_loyalty_modifier":"0.05"},"secondaryCountry":{"adm_tech_cost_modifier":"-0.1","stability_cost_modifier":"-0.1"}},{"name":"godlost","color":{"red":55,"green":59,"blue":67},"country":{"tolerance_heathen":"2","discipline":"0.05"},"secondaryCountry":{"army_tradition_decay":"-0.01"}}]},{"name":"kheteratan","defenderOfFaith":false,"canFormPersonalUnions":false,"religions":[{"name":"khetist","color":{"red":252,"green":162,"blue":100},"country":{"tolerance_heathen":"2","tolerance_own":"1"},"secondaryCountry":{"tolerance_heathen":"1","tolerance_own":"1"},"province":{"local_missionary_strength":"-0.02"}},{"name":"mother_akan","color":{"red":200,"green":162,"blue":100},"country":{"defensiveness":"0.1","tolerance_own":"1"},"secondaryCountry":{"defensiveness":"0.1"},"province":{"local_missionary_strength":"-0.02"}}]},{"name":"gnollish","defenderOfFaith":false,"canFormPersonalUnions":false,"religions":[{"name":"xhazobkult","color":{"red":181,"green":230,"blue":29},"country":{"raze_power_gain":"0.2","land_morale":"0.1","artificers_influence_modifier":"-0.05"},"secondaryCountry":{"land_morale":"0.1","raze_power_gain":"0.1"},"province":{"local_missionary_strength":"-0.02"}}]},{"name":"dwarven","defenderOfFaith":false,"canFormPersonalUnions":false,"religions":[{"name":"ancestor_worship","color":{"red":99,"green":99,"blue":99},"country":{"same_culture_advisor_cost":"-0.33","defensiveness":"0.25"},"secondaryCountry":{"same_culture_advisor_cost":"-0.33"}},{"name":"runefather_worship","color":{"red":50,"green":30,"blue":50},"country":{"discipline":"0.05","tolerance_heretic":"-5"},"secondaryCountry":{"discipline":"0.025"},"province":{"trade_goods_size":"0.25"}}]},{"name":"elven","defenderOfFaith":false,"canFormPersonalUnions":false,"religions":[{"name":"elven_forebears","color":{"red":186,"green":241,"blue":248},"country":{"prestige_decay":"-0.02","tolerance_heathen":"2"},"secondaryCountry":{"prestige_decay":"-0.01","tolerance_heathen":"2"}},{"name":"soise_vio","color":{"red":200,"green":170,"blue":180},"country":{"global_unrest":"-1","tolerance_heathen":"-1"},"secondaryCountry":{"global_unrest":"-1"}}]},{"name":"bulwari","defenderOfFaith":true,"canFormPersonalUnions":false,"religions":[{"name":"bulwari_sun_cult","color":{"red":255,"green":201,"blue":14},"country":{"global_unrest":"-2","tolerance_own":"2"},"secondaryCountry":{"global_unrest":"-1","tolerance_own":"1"},"province":{"local_missionary_strength":"-0.02"}},{"name":"old_bulwari_sun_cult","color":{"red":255,"green":67,"blue":24},"country":{"garrison_size":"0.4","tolerance_own":"2"},"secondaryCountry":{"garrison_size":"0.1","tolerance_own":"1"},"province":{"local_defensiveness":"0.1","local_missionary_strength":"-0.03"}},{"name":"the_jadd","color":{"red":255,"green":138,"blue":12},"country":{"num_accepted_cultures":"1","land_morale":"0.1"},"secondaryCountry":{"promote_culture_cost":"-0.25","land_morale":"0.1"},"province":{"local_missionary_strength":"-0.02","local_manpower_modifier":"0.25"}}]},{"name":"gerudian","defenderOfFaith":false,"canFormPersonalUnions":false,"religions":[{"name":"skaldhyrric_faith","color":{"red":255,"green":201,"blue":201},"country":{"stability_cost_modifier":"-0.1","tolerance_own":"2"},"secondaryCountry":{"stability_cost_modifier":"-0.1"},"province":{"local_missionary_strength":"-0.02"}}]},{"name":"orcish","defenderOfFaith":false,"canFormPersonalUnions":false,"religions":[{"name":"great_dookan","color":{"red":43,"green":106,"blue":62},"country":{"land_morale":"0.1","prestige_from_land":"0.25","tolerance_heathen":"-2"},"secondaryCountry":{"land_morale":"0.1"}},{"name":"old_dookan","color":{"red":13,"green":56,"blue":22},"country":{"army_tradition":"0.5","global_unrest":"-1","tolerance_heretic":"-2"},"secondaryCountry":{"army_tradition":"0.3"}}]},{"name":"dragon_cult","defenderOfFaith":false,"canFormPersonalUnions":false,"religions":[{"name":"kobold_dragon_cult","color":{"red":3,"green":85,"blue":124},"country":{"loot_amount":"0.5","tolerance_heretic":"2"},"secondaryCountry":{"loot_amount":"0.2","tolerance_heretic":"2"}},{"name":"drozma_tur","color":{"red":61,"green":179,"blue":26},"country":{"movement_speed":"0.2","diplomatic_reputation":"1"},"secondaryCountry":{"movement_speed":"0.2","diplomatic_reputation":"1"}},{"name":"kobold_serpent_cult","color":{"red":0,"green":200,"blue":50},"country":{"loot_amount":"0.5","tolerance_heretic":"2"},"secondaryCountry":{"loot_amount":"0.2","tolerance_heretic":"2"}}]},{"name":"goblin","defenderOfFaith":false,"canFormPersonalUnions":false,"religions":[{"name":"goblinic_shamanism","color":{"red":127,"green":76,"blue":76},"country":{"tolerance_heathen":"2","loot_amount":"0.10"},"secondaryCountry":{"tolerance_own":"2","loot_amount":"0.25"}}]},{"name":"harpy_cults","defenderOfFaith":false,"canFormPersonalUnions":false,"religions":[{"name":"the_hunt","color":{"red":173,"green":148,"blue":124},"country":{"leader_land_shock":"1","tolerance_heathen":"3"},"secondaryCountry":{"leader_land_shock":"1"}}]},{"name":"aelantiri","defenderOfFaith":false,"canFormPersonalUnions":false,"religions":[{"name":"weeping_mother","color":{"red":255,"green":120,"blue":128},"country":{"global_unrest":"-2","tolerance_own":"1"},"secondaryCountry":{"global_unrest":"-2"},"province":{"local_missionary_strength":"0.02"}},{"name":"death_cult_of_cheshosh","color":{"red":66,"green":66,"blue":66},"country":{"land_morale":"0.1","shock_damage":"0.1"},"secondaryCountry":{"land_morale":"0.1"},"province":{"local_missionary_strength":"0.02"}}]},{"name":"harafe","defenderOfFaith":false,"canFormPersonalUnions":false,"religions":[{"name":"kalun_masks","color":{"red":210,"green":20,"blue":60},"country":{"production_efficiency":"0.1","prestige_decay":"-0.01"},"secondaryCountry":{"production_efficiency":"0.1"},"province":{"local_missionary_strength":"-0.02"}}]},{"name":"effelai","defenderOfFaith":false,"canFormPersonalUnions":false,"religions":[{"name":"tswohvwohii","color":{"red":60,"green":240,"blue":120},"country":{"prestige_decay":"-0.01","tolerance_heretic":"-2"},"secondaryCountry":{"prestige":"0.66"},"province":{"local_missionary_strength":"-0.02"}},{"name":"chahinanito","color":{"red":90,"green":127,"blue":20},"country":{"trade_efficiency":"0.2","tolerance_heathen":"-2"},"secondaryCountry":{"trade_steering":"0.1"},"province":{"local_missionary_strength":"-0.02"}},{"name":"song_servants","color":{"red":235,"green":215,"blue":210},"country":{"garrison_size":"0.15","land_attrition":"-0.1"},"secondaryCountry":{"garrison_size":"0.1"},"province":{"local_defensiveness":"0.1"}},{"name":"orwaii","color":{"red":30,"green":80,"blue":50},"country":{"discipline":"0.05","tolerance_own":"2"},"secondaryCountry":{"discipline":"0.025"},"province":{"local_missionary_strength":"0.01"}},{"name":"leechfather","color":{"red":25,"green":0,"blue":51},"country":{"global_sailors_modifier":"0.1","sailors_recovery_speed":"0.1"},"secondaryCountry":{"hostile_attrition":"1"},"province":{"local_missionary_strength":"0.01"}}]},{"name":"andic","defenderOfFaith":false,"canFormPersonalUnions":false,"religions":[{"name":"kheionism","color":{"red":99,"green":99,"blue":133},"country":{"republican_tradition":"0.25","trade_efficiency":"0.1"},"secondaryCountry":{"trade_efficiency":"0.1"}}]},{"name":"taychendi","defenderOfFaith":false,"canFormPersonalUnions":false,"religions":[{"name":"gods_of_the_taychend","color":{"red":188,"green":181,"blue":73},"country":{"advisor_cost":"-0.25","prestige_decay":"-0.01"},"secondaryCountry":{"advisor_cost":"-0.25"}}]},{"name":"ynnic","defenderOfFaith":false,"canFormPersonalUnions":false,"religions":[{"name":"ynn_river_worship","color":{"red":139,"green":172,"blue":212},"country":{"tolerance_own":"1"},"secondaryCountry":{"reinforce_speed":"0.1"}}]},{"name":"fey_religion","defenderOfFaith":false,"canFormPersonalUnions":false,"religions":[{"name":"fey_court","color":{"red":0,"green":114,"blue":187},"country":{"core_decay_on_your_own":"-0.5","global_unrest":"-1"},"secondaryCountry":{"core_decay_on_your_own":"-0.5"},"province":{"local_monthly_devastation":"-0.1"}},{"name":"eordellon","color":{"red":253,"green":232,"blue":199},"country":{"tolerance_own":"1","development_cost":"-0.1","global_heretic_missionary_strength":"0.015"},"secondaryCountry":{"development_cost":"-0.1"}},{"name":"spring_court","color":{"red":184,"green":228,"blue":80},"country":{"idea_cost":"-0.1","manpower_recovery_speed":"0.1"},"secondaryCountry":{"idea_cost":"-0.1"}},{"name":"summer_court","color":{"red":245,"green":192,"blue":54},"country":{"naval_forcelimit_modifier":"0.25","global_trade_goods_size_modifier":"0.1"},"secondaryCountry":{"navy_tradition":"1"}},{"name":"autumn_court","color":{"red":249,"green":121,"blue":44},"country":{"global_tax_modifier":"0.1","global_unrest":"-1"},"secondaryCountry":{"global_unrest":"-1"}},{"name":"winter_court","color":{"red":202,"green":244,"blue":255},"country":{"global_spy_defence":"0.15","war_exhaustion":"-0.03"},"secondaryCountry":{"global_spy_defence":"0.15"}},{"name":"ashentree_pact","color":{"red":80,"green":200,"blue":160},"country":{"tolerance_own":"3","land_morale":"0.05","tolerance_heathen":"-2"},"secondaryCountry":{"tolerance_own":"1"},"province":{"local_missionary_strength":"-0.02"}}]},{"name":"raheni","defenderOfFaith":false,"canFormPersonalUnions":false,"religions":[{"name":"high_philosophy","color":{"red":73,"green":9,"blue":96},"country":{"global_unrest":"-2","stability_cost_modifier":"-0.2"},"secondaryCountry":{"global_unrest":"-1"},"province":{"local_missionary_strength":"-0.02"}}]},{"name":"halessi","defenderOfFaith":false,"canFormPersonalUnions":false,"religions":[{"name":"righteous_path","color":{"red":222,"green":222,"blue":222},"country":{"tolerance_own":"1"},"secondaryCountry":{"reinforce_speed":"0.1"}},{"name":"lefthand_path","color":{"red":57,"green":57,"blue":57},"country":{"tolerance_own":"1"},"secondaryCountry":{"reinforce_speed":"0.1"}}]},{"name":"triunic_lake","defenderOfFaith":false,"canFormPersonalUnions":false,"religions":[{"name":"kodave_followers","color":{"red":235,"green":88,"blue":48},"country":{"infantry_power":"0.1","tolerance_heathen":"-2"},"secondaryCountry":{"infantry_power":"0.1"},"province":{"garrison_growth":"0.1","local_defensiveness":"0.1"}},{"name":"yukel_followers","color":{"red":160,"green":160,"blue":160},"country":{"trade_efficiency":"0.1","tolerance_heretic":"2"},"secondaryCountry":{"trade_efficiency":"0.1"},"province":{"trade_value_modifier":"0.1"}},{"name":"enuuk_followers","color":{"red":225,"green":181,"blue":55},"country":{"production_efficiency":"0.1"},"secondaryCountry":{"production_efficiency":"0.1"},"province":{"local_development_cost":"-0.1"}},{"name":"kalyin_worshippers","color":{"red":100,"green":127,"blue":200},"country":{"global_trade_goods_size_modifier":"0.1","infantry_power":"0.05","tolerance_heretic":"-2"},"secondaryCountry":{"global_trade_goods_size_modifier":"0.1"},"province":{"trade_value_modifier":"0.1"}}]},{"name":"giantkin","defenderOfFaith":false,"canFormPersonalUnions":false,"religions":[{"name":"feast_of_the_gods","color":{"red":120,"green":127,"blue":89},"country":{"prestige_from_land":"0.3","global_manpower_modifier":"0.1"},"secondaryCountry":{"prestige_from_land":"0.25"},"province":{"supply_limit_modifier":"0.15"}},{"name":"mountain_watchers","color":{"red":41,"green":41,"blue":77},"country":{"movement_speed":"0.10","defensiveness":"0.15"},"secondaryCountry":{"movement_speed":"0.075","defensiveness":"0.05"},"province":{"local_hostile_attrition":"1"}}]},{"name":"centaur_religion","defenderOfFaith":false,"canFormPersonalUnions":false,"religions":[{"name":"ik_magthaal","color":{"red":60,"green":40,"blue":20},"country":{"cavalry_shock":"0.25","horde_unity":"1"},"secondaryCountry":{"cavalry_shock":"0.25"}}]}]}